SinhalaSubBulk/__init__.py
SinhalaSubBulk-2.0.0.dist-info/METADATA
SinhalaSubBulk-2.0.0.dist-info/WHEEL
SinhalaSubBulk-2.0.0.dist-info/top_level.txt
SinhalaSubBulk-2.0.0.dist-info/RECORD
