Metadata-Version: 2.1
Name: SinhalaSubBulk
Version: 2.0.0
Summary: A Python library for Download Bulk of Sinhala Subtitles.
Home-page: 
Author: Gavindu Tharaka
Author-email: gavi.tharaka@gmail.com
Classifier: Programming Language :: Python :: 3
Classifier: License :: OSI Approved :: MIT License
Classifier: Operating System :: OS Independent
Requires-Python: >=3.6
Requires-Dist: beautifulsoup4 (==4.9.3)
Requires-Dist: requests (==2.25.1)
